modelcli/__init__.py
modelcli/cli.py
modelcli-0.1.0.dist-info/METADATA
modelcli-0.1.0.dist-info/WHEEL
modelcli-0.1.0.dist-info/entry_points.txt
modelcli-0.1.0.dist-info/top_level.txt
modelcli-0.1.0.dist-info/RECORD
