Metadata-Version: 2.4
Name: modelcli
Version: 0.1.0
Summary: Universal CLI for sending prompts to any LLM model and provider.
Home-page: https://github.com/Tomigambii/modelcli
Author: Tomás Gambirassi
Author-email: tomasgambirassi@gmail.com
Requires-Python: >=3.7
Requires-Dist: requests
Dynamic: author
Dynamic: author-email
Dynamic: description
Dynamic: home-page
Dynamic: requires-dist
Dynamic: requires-python
Dynamic: summary
